[
  {
    "AppID": "753",
    "AppContext": 6,
    "IconURL": null,
    "IconPath": "Icons/steam.png",
    "Name": "Steam"
  },
  {
    "AppID": "730",
    "AppContext": 2,
    "IconURL": null,
    "IconPath": "Icons/csgo.png",
    "Name": "Counter-Strike: Global Offensive"
  },
  {
    "AppID": "570",
    "AppContext": 2,
    "IconURL": null,
    "IconPath": "Icons/dota.png",
    "Name": "Dota 2"
  },
  {
    "AppID": "440",
    "AppContext": 2,
    "IconURL": null,
    "IconPath": "Icons/tf.png",
    "Name": "Team Fortress 2"
  },
  {
    "AppID": "578080",
    "AppContext": 2,
    "IconURL": null,
    "IconPath": "Icons/pubg.png",
    "Name": "PLAYERUNKNOWN'S BATTLEGROUNDS"
  },
  {
    "AppID": "433850",
    "AppContext": 1,
    "IconURL": null,
    "IconPath": "Icons/h1z1.png",
    "Name": "H1Z1"
  },
  {
    "AppID": "218620",
    "AppContext": 2,
    "IconURL": null,
    "IconPath": "Icons/pd2.png",
    "Name": "PAYDAY 2"
  },
  {
    "AppID": "252490",
    "AppContext": 2,
    "IconURL": null,
    "IconPath": "Icons/rust.png",
    "Name": "Rust"
  },
  {
    "AppID": "232090",
    "AppContext": 2,
    "IconURL": null,
    "IconPath": "Icons/kf2.png",
    "Name": "Killing Floor 2"
  },
  {
    "AppID": "244850",
    "AppContext": 2,
    "IconURL": null,
    "IconPath": "Icons/se.png",
    "Name": "Space Engineers"
  },
  {
    "AppID": "304930",
    "AppContext": 2,
    "IconURL": null,
    "IconPath": "Icons/unturned.png",
    "Name": "Unturned"
  }
]
